oibot/__init__.py
oibot/bot.py
oibot/matcher.py
oibot/plugin.py
oibot/api/__init__.py
oibot/api/access_token.py
oibot/api/recall_message.py
oibot/api/send_message.py
oibot/api/upload_file.py
oibot/event/__init__.py
oibot/event/c2c_message_create.py
oibot/event/friend_add.py
oibot/event/friend_del.py
oibot/event/group_add_robot.py
oibot/event/group_at_message_create.py
oibot/event/group_del_robot.py
oibot-2025.7.27.dist-info/METADATA
oibot-2025.7.27.dist-info/WHEEL
oibot-2025.7.27.dist-info/licenses/LICENSE
oibot-2025.7.27.dist-info/RECORD
