Metadata-Version: 2.4
Name: OiBot
Version: 2025.7.27
Summary: a lightweight bot framework
License: MIT License
License-File: LICENSE
Requires-Python: >=3
Requires-Dist: aiohttp
Requires-Dist: cryptography
